odoo/addons/web_leaflet_lib/README.rst
odoo/addons/web_leaflet_lib/__init__.py
odoo/addons/web_leaflet_lib/__manifest__.py
odoo/addons/web_leaflet_lib/data/ir_config_parameter.xml
odoo/addons/web_leaflet_lib/demo/ir_config_parameter.xml
odoo/addons/web_leaflet_lib/i18n/fr.po
odoo/addons/web_leaflet_lib/i18n/it.po
odoo/addons/web_leaflet_lib/i18n/web_leaflet_lib.pot
odoo/addons/web_leaflet_lib/models/__init__.py
odoo/addons/web_leaflet_lib/models/ir_http.py
odoo/addons/web_leaflet_lib/readme/CONFIGURE.md
odoo/addons/web_leaflet_lib/readme/CONTRIBUTORS.md
odoo/addons/web_leaflet_lib/readme/CREDITS.md
odoo/addons/web_leaflet_lib/readme/DESCRIPTION.md
odoo/addons/web_leaflet_lib/static/description/icon.png
odoo/addons/web_leaflet_lib/static/description/index.html
odoo/addons/web_leaflet_lib/static/lib/leaflet/leaflet.css
odoo/addons/web_leaflet_lib/static/lib/leaflet/leaflet.js
odoo/addons/web_leaflet_lib/static/lib/leaflet/images/layers-2x.png
odoo/addons/web_leaflet_lib/static/lib/leaflet/images/layers.png
odoo/addons/web_leaflet_lib/static/lib/leaflet/images/marker-icon-2x.png
odoo/addons/web_leaflet_lib/static/lib/leaflet/images/marker-icon.png
odoo/addons/web_leaflet_lib/static/lib/leaflet/images/marker-shadow.png
odoo_addon_web_leaflet_lib-18.0.1.0.1.dist-info/METADATA
odoo_addon_web_leaflet_lib-18.0.1.0.1.dist-info/WHEEL
odoo_addon_web_leaflet_lib-18.0.1.0.1.dist-info/top_level.txt
odoo_addon_web_leaflet_lib-18.0.1.0.1.dist-info/RECORD
